encode_utils_cli/__init__.py
encode_utils_cli/__main__.py
encode_utils_cli/_cli.py
encode_utils_cli/chapt2bmqpyml.py
encode_utils_cli/frames_denum.py
encode_utils_cli/mpls2chap.py
encode_utils_cli/num_frames.py
encode_utils_cli/re_chapters.py
encode_utils_cli/re_titles.py
encode_utils_cli/screens2bm.py
encode_utils_cli/vs_screens.py
encode_utils_cli/zones_validator.py
encode_utils_cli/util/__init__.py
encode_utils_cli/util/load_mpls.py
encode_utils_cli/util/source.py
encode_utils_cli/util/timeconv.py
encode_utils_cli-1.1.0.dist-info/METADATA
encode_utils_cli-1.1.0.dist-info/WHEEL
encode_utils_cli-1.1.0.dist-info/entry_points.txt
encode_utils_cli-1.1.0.dist-info/licenses/LICENSE
encode_utils_cli-1.1.0.dist-info/RECORD
