Metadata-Version: 2.4
Name: encode-utils-cli
Version: 1.1.0
Summary: Encode utils collection
Project-URL: Repository, https://github.com/deadnews/encode-utils-cli
Project-URL: Changelog, https://github.com/deadnews/encode-utils-cli/CHANGELOG.md
Project-URL: Documentation, https://deadnews.github.io/encode-utils-cli
Author-email: deadnews <deadnewsgit@gmail.com>
License-Expression: MIT
License-File: LICENSE
Keywords: cli,encode,mpls,vapoursynth
Classifier: Environment :: Console
Classifier: Operating System :: OS Independent
Classifier: Topic :: Multimedia :: Video
Requires-Python: >=3.11
Requires-Dist: click>=8.1.7
Requires-Dist: pyperclip>=1.9.0
Requires-Dist: pyyaml>=6.0.2
Requires-Dist: schema>=0.7.5
Requires-Dist: vapoursynth>=72
